s2gpp-1.0.2.dist-info/METADATA
s2gpp-1.0.2.dist-info/WHEEL
s2gpp-1.0.2.dist-info/license_files/LICENSE
s2gpp.libs/libquadmath-bef5612d.so.0
s2gpp/__init__.py
s2gpp/s2gpp.cpython-38-x86_64-linux-gnu.so
s2gpp-1.0.2.dist-info/RECORD
