Metadata-Version: 2.1
Name: s2gpp
Version: 1.0.2
Classifier: Programming Language :: Python
Requires-Dist: scikit-learn~=1.1
License-File: LICENSE
Summary: Algorithm for Highly Efficient Detection of Correlation Anomalies in Multivariate Time Series
Home-Page: https://github.com/HPI-Information-Systems/S2Gpp
Author: Phillip Wenig <phillip.wenig@hpi.de>
Author-email: Phillip Wenig <phillip.wenig@hpi.de>
License: MIT
Project-URL: homepage, https://github.com/HPI-Information-Systems/S2Gpp
Project-URL: repository, https://github.com/HPI-Information-Systems/S2Gpp
